nbstatic/__init__.py
nbstatic/__main__.py
nbstatic/core.py
nbstatic/logger.py
nbstatic/commands/__init__.py
nbstatic/commands/argparse_helpers.py
nbstatic/commands/convert.py
nbstatic/commands/execute.py
nbstatic/tests/__init__.py
nbstatic/tests/test_cli.py
nbstatic/tests/test_nbstatic.py
nbstatic/tests/data/exception-should-fail.ipynb
nbstatic/tests/data/exception-should-pass.ipynb
nbstatic/tests/data/my_notebooks/notebook1.ipynb
nbstatic/tests/data/my_notebooks/sub_path1/notebook2.ipynb
nbstatic/tests/data/my_notebooks/sub_path1/notebook3.ipynb
nbstatic/tests/data/nb_test1/notebook1.ipynb
nbstatic/tests/data/nb_test2/notebook1.ipynb
nbstatic/tests/data/nb_test2/notebook2.ipynb
nbstatic/tests/data/nb_test3/nb1/notebook1.ipynb
nbstatic/tests/data/nb_test3/nb2/notebook2.ipynb
nbstatic-0.1.dist-info/LICENSE
nbstatic-0.1.dist-info/METADATA
nbstatic-0.1.dist-info/WHEEL
nbstatic-0.1.dist-info/entry_points.txt
nbstatic-0.1.dist-info/top_level.txt
nbstatic-0.1.dist-info/RECORD
